perf_metric_xtr/__init__.py
perf_metric_xtr/main.py
perf_metric_xtr/prompts.py
perf_metric_xtr-2025.12.21195642.dist-info/METADATA
perf_metric_xtr-2025.12.21195642.dist-info/WHEEL
perf_metric_xtr-2025.12.21195642.dist-info/top_level.txt
perf_metric_xtr-2025.12.21195642.dist-info/RECORD
