Metadata-Version: 2.4
Name: perf-metric-xtr
Version: 2025.12.21195642
Summary: perf-metric-xtr extracts key performance metrics from tech announcements and outputs standardized summaries.
Author-email: perf-metric-xtr <hi@eugene.plus>
License: MIT
Project-URL: Homepage, https://github.com/chigwell/perf-metric-xtr
Requires-Python: >=3.9
Requires-Dist: langchain-llm7>=0.0.0
Requires-Dist: llmatch-messages>=0.0.0
Requires-Dist: langchain-core>=0.3.0
